latteries/__init__.py
latteries/cache.py
latteries/caller.py
latteries/load_caller.py
latteries/log_probs.py
latteries/moderation.py
latteries/shared.py
latteries/viewer.py
latteries-0.1.5.dist-info/METADATA
latteries-0.1.5.dist-info/WHEEL
latteries-0.1.5.dist-info/entry_points.txt
latteries-0.1.5.dist-info/RECORD
