Metadata-Version: 2.4
Name: latteries
Version: 0.1.5
Summary: James' API LLM evaluations workflow library - A collection of tools for LLM API calls, caching, and evaluation workflows
Project-URL: Homepage, https://github.com/thejaminator/latteries
Project-URL: Repository, https://github.com/thejaminator/latteries
Project-URL: Issues, https://github.com/thejaminator/latteries/issues
Author-email: James <your-email@example.com>
License: MIT
Keywords: anthropic,api,caching,evaluation,llm,openai
Classifier: Development Status :: 3 - Alpha
Classifier: Intended Audience :: Developers
Classifier: Intended Audience :: Science/Research
Classifier: License :: OSI Approved :: MIT License
Classifier: Programming Language :: Python :: 3
Classifier: Programming Language :: Python :: 3.8
Classifier: Programming Language :: Python :: 3.9
Classifier: Programming Language :: Python :: 3.10
Classifier: Programming Language :: Python :: 3.11
Classifier: Programming Language :: Python :: 3.12
Classifier: Topic :: Scientific/Engineering :: Artificial Intelligence
Classifier: Topic :: Software Development :: Libraries :: Python Modules
Requires-Python: >=3.8
Requires-Dist: anthropic>=0.25.0
Requires-Dist: anyio
Requires-Dist: httpx
Requires-Dist: openai>=1.0.0
Requires-Dist: pydantic>=2.0.0
Requires-Dist: slist
Requires-Dist: streamlit
Requires-Dist: tqdm
Provides-Extra: dev
Requires-Dist: black; extra == 'dev'
Requires-Dist: pyright; extra == 'dev'
Requires-Dist: pytest; extra == 'dev'
Requires-Dist: pytest-asyncio; extra == 'dev'
Requires-Dist: ruff; extra == 'dev'
